LICENSE.txt
MANIFEST.in
README.rst
setup.cfg
setup.py
pattern3/__init__.py
pattern3/canvas.js
pattern3/metrics.py
pattern3.egg-info/PKG-INFO
pattern3.egg-info/SOURCES.txt
pattern3.egg-info/dependency_links.txt
pattern3.egg-info/requires.txt
pattern3.egg-info/top_level.txt
pattern3.egg-info/zip-safe
pattern3/db/__init__.py
pattern3/graph/__init__.py
pattern3/graph/commonsense.csv
pattern3/graph/commonsense.py
pattern3/graph/graph.js
pattern3/server/__init__.py
pattern3/server/static/robots.txt
pattern3/text/__init__.py
pattern3/text/search.py
pattern3/text/tree.py
pattern3/text/de/__init__.py
pattern3/text/de/__main__.py
pattern3/text/de/de-context.txt
pattern3/text/de/de-frequency.txt
pattern3/text/de/de-lexicon.txt
pattern3/text/de/de-morphology.txt
pattern3/text/de/de-spelling.txt
pattern3/text/de/de-verbs.txt
pattern3/text/de/inflect.py
pattern3/text/en/__init__.py
pattern3/text/en/__main__.py
pattern3/text/en/en-context.txt
pattern3/text/en/en-entities.txt
pattern3/text/en/en-frequency.txt
pattern3/text/en/en-lexicon.txt
pattern3/text/en/en-model.slp
pattern3/text/en/en-morphology.txt
pattern3/text/en/en-sentiment.xml
pattern3/text/en/en-spelling.txt
pattern3/text/en/en-verbs.txt
pattern3/text/en/inflect.py
pattern3/text/en/inflect_quantify.py
pattern3/text/en/modality.py
pattern3/text/en/wordlist/__init__.py
pattern3/text/en/wordlist/academic.txt
pattern3/text/en/wordlist/basic.txt
pattern3/text/en/wordlist/profanity.txt
pattern3/text/en/wordlist/stopwords.txt
pattern3/text/en/wordlist/time.txt
pattern3/text/en/wordnet/__init__.py
pattern3/text/en/wordnet/resnik-ic2.txt
pattern3/text/en/wordnet/resnik-ic3.txt
pattern3/text/en/wordnet/dict/LICENSE.txt
pattern3/text/en/wordnet/dict/data.adj
pattern3/text/en/wordnet/dict/data.adv
pattern3/text/en/wordnet/dict/data.noun1
pattern3/text/en/wordnet/dict/data.noun2
pattern3/text/en/wordnet/dict/data.verb
pattern3/text/en/wordnet/dict/index.32
pattern3/text/en/wordnet/dict/index.adj
pattern3/text/en/wordnet/dict/index.adv
pattern3/text/en/wordnet/dict/index.noun
pattern3/text/en/wordnet/dict/index.sense
pattern3/text/en/wordnet/dict/index.verb
pattern3/text/en/wordnet/dict/lexnames
